sreup/Client.py
sreup/ThreadMain.py
sreup/__init__.py
sreup/common/Requests.py
sreup/common/__init__.py
sreup/common/config.py
sreup/common/utils.py
sreup/selenium/__init__.py
sreup/selenium/elements.py
sreup/selenium/locators.py
sreup/selenium/page.py
sreup-0.49.dist-info/METADATA
sreup-0.49.dist-info/WHEEL
sreup-0.49.dist-info/top_level.txt
sreup-0.49.dist-info/RECORD
