Metadata-Version: 2.1
Name: sreup
Version: 0.49
Summary: A Des of sreup
Home-page: https://github.com/vtandroid/sreup
Author: hoa
Author-email: getmoneykhmt3@gmail.com
License: UNKNOWN
Platform: UNKNOWN
Classifier: Programming Language :: Python :: 3
Classifier: License :: OSI Approved :: MIT License
Classifier: Operating System :: OS Independent
Requires-Dist: selenium
Requires-Dist: requests
Requires-Dist: gbak
